README.md
setup.cfg
setup.py
grevillea/__init__.py
grevillea/py.typed
grevillea.egg-info/PKG-INFO
grevillea.egg-info/SOURCES.txt
grevillea.egg-info/dependency_links.txt
grevillea.egg-info/top_level.txt