Metadata-Version: 2.1
Name: grevillea
Version: 0.0.1
Summary: Google Cloud Functions support for ASGI
Home-page: https://github.com/erm/grevillea
Author: Jordan Eremieff
Author-email: jordan@eremieff.com
License: MIT
Platform: UNKNOWN
Classifier: License :: OSI Approved :: MIT License
Classifier: Operating System :: OS Independent
Classifier: Programming Language :: Python :: 3.7
Requires-Python: ~=3.7
